[
    {
        "name": "lattice.scope.cache.lookup.request",
        "thread": "lattice.scope.cache.requests",
        "availability": "now",
        "intent": {
            "schema": {
                "state": "Bound",
                "value": "rhex://schema.lattice.scope.cache.request"
            },
            "data": {
                "kind": "Json",
                "value": {
                    "scope": "test"
                }
            }
        },
        "meta": {
            "creator": "what.the.fuck.ever",
            "timestamp": 0
        }
    },
    {
        "name": "system.ip_address",
        "thread": "system.ip_address",
        "availability": "now",
        "intent": {
            "schema": {
                "state": "Bound",
                "value": "rhex://schema.system.ip_address"
            },
            "data": {
                "kind": "Json",
                "value": {
                    "ip_addr": "127.0.0.1",
                    "port": 1984
                }
            }
        },
        "meta": {
            "creator": "what.the.fuck.ever",
            "timestamp": 0
        }
    },
    {
        "name": "lattice.scope.cache.table",
        "thread": "lattice.scope.cache.table",
        "availability": "now",
        "intent": {
            "schema": {
                "state": "Bound",
                "value": "rhex://schema.lattice.scope.cache.table"
            },
            "data": {
                "kind": "Binary",
                "value": {
                    "encoding": "base64",
                    "data": "oA=="
                }
            }
        },
        "meta": {
            "creator": "what.the.fuck.ever",
            "timestamp": 0
        }
    },
    {
        "name": "crypto.ed25519.generate.1",
        "thread": "crypto.ed25519.generate",
        "availability": "now",
        "intent": {
            "schema": {
                "state": "Bound",
                "value": "rhex://schema.crypto.ed25519.generate"
            },
            "data": {
                "kind": "None",
                "value": null
            }
        },
        "meta": {
            "creator": "what.the.fuck.ever",
            "timestamp": 0
        }
    }
]
